emslogging/__init__.py
emslogging/log.py
ems_logging-0.0.3.dist-info/LICENSE
ems_logging-0.0.3.dist-info/METADATA
ems_logging-0.0.3.dist-info/WHEEL
ems_logging-0.0.3.dist-info/top_level.txt
ems_logging-0.0.3.dist-info/RECORD
