Metadata-Version: 2.1
Name: ems-logging
Version: 0.0.3
Summary: Common logging for EMS projects
Home-page: https://github.com/
Author: Jesper Halkjær Jensen
Author-email: gedemagt@gmail.com
License: MIT
Platform: UNKNOWN
Requires-Python: >=2.7
